pyfcach.py
pyfcach-0.2.13.dist-info/METADATA
pyfcach-0.2.13.dist-info/WHEEL
pyfcach-0.2.13.dist-info/top_level.txt
pyfcach-0.2.13.dist-info/RECORD
