Metadata-Version: 2.4
Name: pyfcach
Version: 0.2.13
Summary: Ultra Fast Cache
Author-email: Sarix <m00263277@gmail.com>
License: Apache-2.0
Requires-Python: >=3.8
Requires-Dist: sympy
Requires-Dist: xxhash
Requires-Dist: b64fx
